ut2chartrender/__init__.py
ut2chartrender/app.py
ut2chartrender/chart.py
ut2chartrender/main.py
ut2chartrender/renderer.py
ut2chartrender/settings.py
ut2chartrender-0.0.6.dist-info/METADATA
ut2chartrender-0.0.6.dist-info/WHEEL
ut2chartrender-0.0.6.dist-info/top_level.txt
ut2chartrender-0.0.6.dist-info/RECORD
