Metadata-Version: 2.1
Name: ut2chartrender
Version: 0.0.6
Summary: Library that takes as input config and datasets for highcharts, and outputs SVG image of rendered chart
Home-page: https://gitlab.com/jc4ut/renderer
Author: JC
Author-email: jencat@ex.ua
License: UNKNOWN
Platform: UNKNOWN
Requires-Python: >=3.7
Requires-Dist: wheel (==0.33.6)
Requires-Dist: python-highcharts (==0.4.2)
Requires-Dist: selenium (==3.141.0)
Requires-Dist: beautifulsoup4 (==4.8.2)
